main.py
mseep_africas_talking_airtime_mcp_server-0.1.2.dist-info/licenses/LICENSE
mseep_africas_talking_airtime_mcp_server-0.1.2.dist-info/METADATA
mseep_africas_talking_airtime_mcp_server-0.1.2.dist-info/WHEEL
mseep_africas_talking_airtime_mcp_server-0.1.2.dist-info/entry_points.txt
mseep_africas_talking_airtime_mcp_server-0.1.2.dist-info/top_level.txt
mseep_africas_talking_airtime_mcp_server-0.1.2.dist-info/RECORD
