Metadata-Version: 2.4
Name: mseep-africas-talking-airtime-mcp-server
Version: 0.1.2
Summary: An MCP server that provides tools for interacting with Africa's Talking airtime service.
Author-email: mseep <support@skydeck.ai>
Requires-Python: >=3.12
License-File: LICENSE
Requires-Dist: africastalking>=1.2.9
Requires-Dist: mcp[cli]>=1.6.0
Dynamic: license-file
